{
  "osm": {
    "layers": {
      "land_ohm_lines":             "admin_boundaries_lines",
      "land_ohm_centroids":         "admin_boundaries_centroids",
      "land_ohm_maritime":          "admin_maritime_lines",
      "place_areas":                "place_areas",
      "place_points_centroids":     "place_points_centroids",
      "water_areas":                "water_areas",
      "water_areas_centroids":      "water_areas_centroids",
      "water_lines":                "water_lines",
      "transport_areas":            "transport_areas",
      "transport_lines":            "transport_lines",
      "route_lines":                "routes_indexed",
      "transport_points_centroids": "transport_points_centroids",
      "amenity_areas":              "amenity_areas",
      "amenity_points_centroids":   "amenity_points_centroids",
      "buildings":                  "buildings_areas",
      "buildings_points_centroids": "buildings_points_centroids",
      "landuse_areas":              "landuse_areas",
      "landuse_points_centroids":   "landuse_points_centroids",
      "landuse_lines":              "landuse_lines",
      "other_areas":                "other_areas",
      "other_points_centroids":     "other_points_centroids",
      "other_lines":                "other_lines"
    }
  },
  "ne": {
    "cache": "30d",
    "layers": {
      "ne_water_areas":             "ne_lakes"
    }
  },
  "osm_land": {
    "cache": "30d",
    "layers": {
      "land":                       "land"
    }
  },
  "ohm_admin": {
    "layers": {
      "boundaries":                 "admin_boundaries_areas"
    }
  }
}
